MANIFEST.in
README.rst
requirements.txt
setup.py
pocounit/__init__.py
pocounit/assets_manager.py
pocounit/case.py
pocounit/fixture.py
pocounit/runner.py
pocounit/suite.py
pocounit.egg-info/PKG-INFO
pocounit.egg-info/SOURCES.txt
pocounit.egg-info/dependency_links.txt
pocounit.egg-info/requires.txt
pocounit.egg-info/top_level.txt
pocounit/addons/__init__.py
pocounit/addons/airtest/__init__.py
pocounit/addons/airtest/action_tracking.py
pocounit/addons/airtest/polyfill.py
pocounit/addons/airtest/utils.py
pocounit/addons/hunter/__init__.py
pocounit/addons/hunter/runtime_logging.py
pocounit/addons/poco/__init__.py
pocounit/addons/poco/action_tracking.py
pocounit/addons/poco/capturing.py
pocounit/result/__init__.py
pocounit/result/action.py
pocounit/result/app_runtime.py
pocounit/result/assertion.py
pocounit/result/collector.py
pocounit/result/emitter.py
pocounit/result/logger.py
pocounit/result/metainfo.py
pocounit/result/record.py
pocounit/result/runner_runtime.py
pocounit/result/site_snapshot.py
pocounit/result/trace.py
pocounit/utils/__init__.py
pocounit/utils/misc.py
pocounit/utils/outcome.py
pocounit/utils/trace.py
test/__init__.py
test/test_runner.py
test/poco_uiautomation_android/__init__.py
test/poco_uiautomation_android/simple.py