Metadata-Version: 1.0
Name: pocounit
Version: 1.0.40
Summary: Unittest framework for poco and airtest
Home-page: UNKNOWN
Author: UNKNOWN
Author-email: UNKNOWN
License: Apache License 2.0
Keywords: PocoUnit unittest
Platform: UNKNOWN
